{
    "fluentMethods": true,
    "relationships": [
        {
            "relationshipType": "one-to-one",
            "relationshipName": "user",
            "otherEntityName": "user",
            "otherEntityField": "id",
            "ownerSide": true,
            "otherEntityRelationshipName": "person"
        }
    ],
    "fields": [
        {
            "fieldName": "name",
            "fieldType": "String"
        },
        {
            "fieldName": "description",
            "fieldType": "String"
        },
        {
            "fieldName": "themeUrl",
            "fieldType": "String"
        },
        {
            "fieldName": "avatarUrl",
            "fieldType": "String"
        },
        {
            "fieldName": "type",
            "fieldType": "String"
        },
        {
            "fieldName": "sex",
            "fieldType": "String"
        },
        {
            "fieldName": "phone",
            "fieldType": "String"
        },
        {
            "fieldName": "email",
            "fieldType": "String"
        },
        {
            "fieldName": "idCard",
            "fieldType": "String"
        },
        {
            "fieldName": "idGame",
            "fieldType": "String"
        }
    ],
    "changelogDate": "20170206063318",
    "entityTableName": "person",
    "dto": "no",
    "pagination": "pagination",
    "service": "no"
}